aiger_cnf/__init__.py
aiger_cnf/cnf.py
aiger_cnf/test_cnf.py
py_aiger_cnf-5.0.7.dist-info/LICENSE
py_aiger_cnf-5.0.7.dist-info/WHEEL
py_aiger_cnf-5.0.7.dist-info/METADATA
py_aiger_cnf-5.0.7.dist-info/RECORD
