Metadata-Version: 2.1
Name: py-aiger-cnf
Version: 5.0.7
Summary: Python library to convert between AIGER and CNF
Home-page: https://github.com/mvcisback/py-aiger-cnf
License: MIT
Author: Marcell Vazquez-Chanlatte
Author-email: mvc@linux.com
Requires-Python: >=3.7,<4.0
Classifier: License :: OSI Approved :: MIT License
Classifier: Programming Language :: Python :: 3
Classifier: Programming Language :: Python :: 3.10
Classifier: Programming Language :: Python :: 3.7
Classifier: Programming Language :: Python :: 3.8
Classifier: Programming Language :: Python :: 3.9
Requires-Dist: bidict (>=0.22.0,<0.23.0)
Requires-Dist: funcy (>=1.12,<2.0)
Requires-Dist: py-aiger (>=6.0.0,<7.0.0)
Project-URL: Repository, https://github.com/mvcisback/py-aiger-cnf
